<?xml version="1.0" encoding="utf-8"?>
<!--~
  ~ @package   admintools
  ~ @copyright Copyright (c)2010-2023 Nicholas K. Dionysopoulos / Akeeba Ltd
  ~ @license   GNU General Public License version 3, or later
  -->

<form addfieldprefix="Akeeba\Component\AdminTools\Administrator\Field">
    <fields name="filter">
        <field
                name="search"
                type="text"
                inputmode="search"
                label="JSEARCH_FILTER"
                hint="JSEARCH_FILTER"
        />

        <field
                name="status"
                type="list"
                label="COM_ADMINTOOLS_SCANALERTS_LBL_STATUS"
                onchange="this.form.submit();"
        >
            <option value="">COM_ADMINTOOLS_SCANALERTS_LBL_STATUS_SELECT</option>
            <option value="new">COM_ADMINTOOLS_SCANALERTS_LBL_STATUS_NEW</option>
            <option value="suspicious">COM_ADMINTOOLS_SCANALERTS_LBL_STATUS_SUSPICIOUS</option>
            <option value="modified">COM_ADMINTOOLS_SCANALERTS_LBL_STATUS_MODIFIED</option>
        </field>

        <field
                name="acknowledged"
                type="list"
                label="COM_ADMINTOOLS_SCANALERTS_LBL_ACKNOWLEDGED"
                onchange="this.form.submit();"
        >
            <option value="">COM_ADMINTOOLS_SCANALERTS_LBL_ACKNOWLEDGED_SELECT</option>
            <option value="1">COM_ADMINTOOLS_SCANALERTS_LBL_ACKNOWLEDGED_SAFE</option>
            <option value="0">COM_ADMINTOOLS_SCANALERTS_LBL_ACKNOWLEDGED_UNSAFE</option>
        </field>

    </fields>

    <fields name="list">
        <field
                name="fullordering"
                type="list"
                label="JGLOBAL_SORT_BY"
                statuses="*,0,1"
                onchange="this.form.submit();"
                default="id DESC"
                validate="options"
        >
            <option value="">JGLOBAL_SORT_BY</option>
            <option value="id ASC">JGRID_HEADING_ID_ASC</option>
            <option value="id DESC">JGRID_HEADING_ID_DESC</option>
            <option value="scanstart ASC">JDATE_ASC</option>
            <option value="scanstart DESC">JDATE_DESC</option>
            <option value="threat_score ASC">COM_ADMINTOOLS_SCANALERTS_LBL_SORT_THREATSCORE_ASC</option>
            <option value="threat_score DESC">COM_ADMINTOOLS_SCANALERTS_LBL_SORT_THREATSCORE_DESC</option>
            <option value="filestatus ASC">COM_ADMINTOOLS_SCANALERTS_LBL_SORT_STATUS_ASC</option>
            <option value="filestatus DESC">COM_ADMINTOOLS_SCANALERTS_LBL_SORT_STATUS_DESC</option>
            <option value="path ASC">COM_ADMINTOOLS_SCANALERTS_LBL_SORT_PATH_ASC</option>
            <option value="path DESC">COM_ADMINTOOLS_SCANALERTS_LBL_SORT_PATH_DESC</option>
            <option value="acknowledged ASC">COM_ADMINTOOLS_SCANALERTS_LBL_SORT_ACKNOWLEDGED_ASC</option>
            <option value="acknowledged DESC">COM_ADMINTOOLS_SCANALERTS_LBL_SORT_ACKNOWLEDGED_DESC</option>
        </field>

        <field
                name="limit"
                type="limitbox"
                label="JGLOBAL_LIST_LIMIT"
                default="25"
                onchange="this.form.submit();"
        />
    </fields>
</form>